blazeweb/__init__.py
blazeweb/application.py
blazeweb/commands.py
blazeweb/config.py
blazeweb/content.py
blazeweb/events.py
blazeweb/exceptions.py
blazeweb/globals.py
blazeweb/hierarchy.py
blazeweb/logs.py
blazeweb/mail.py
blazeweb/middleware.py
blazeweb/nose_plugin.py
blazeweb/paster_tpl.py
blazeweb/pytest_plugin.py
blazeweb/registry.py
blazeweb/routing.py
blazeweb/scripting.py
blazeweb/tasks.py
blazeweb/testing.py
blazeweb/users.py
blazeweb/version.txt
blazeweb/views.py
blazeweb/wrappers.py
blazeweb/paster_tpls/minimal-project/MANIFEST.in_tmpl
blazeweb/paster_tpls/minimal-project/ez_setup.py
blazeweb/paster_tpls/minimal-project/setup.py_tmpl
blazeweb/paster_tpls/minimal-project/+package+/__init__.py
blazeweb/paster_tpls/minimal-project/+package+/application.py_tmpl
blazeweb/paster_tpls/minimal-project/+package+/settings.py_tmpl
blazeweb/paster_tpls/minimal-project/+package+/views.py
blazeweb/paster_tpls/plugin/__init__.py
blazeweb/paster_tpls/plugin/commands.py
blazeweb/paster_tpls/plugin/content.py
blazeweb/paster_tpls/plugin/events.py
blazeweb/paster_tpls/plugin/forms.py
blazeweb/paster_tpls/plugin/helpers.py
blazeweb/paster_tpls/plugin/views.py
blazeweb/paster_tpls/plugin/config/__init__.py
blazeweb/paster_tpls/plugin/config/settings.py
blazeweb/paster_tpls/plugin/lib/__init__.py
blazeweb/paster_tpls/plugin/model/__init__.py
blazeweb/paster_tpls/plugin/model/actions.py
blazeweb/paster_tpls/plugin/model/helpers.py
blazeweb/paster_tpls/plugin/model/metadata.py
blazeweb/paster_tpls/plugin/model/orm.py
blazeweb/paster_tpls/plugin/model/queries.py
blazeweb/paster_tpls/plugin/tasks/__init__.py
blazeweb/paster_tpls/plugin/templates/index.html
blazeweb/paster_tpls/plugin/tests/__init__.py
blazeweb/paster_tpls/plugin/tests/test_functional.py
blazeweb/paster_tpls/plugin/tests/test_model.py
blazeweb/paster_tpls/plugin/tests/test_unit.py
blazeweb/paster_tpls/project/+dot+hgeol
blazeweb/paster_tpls/project/+dot+hgignore
blazeweb/paster_tpls/project/MANIFEST.in
BlazeWeb-0.6.2.dist-info/METADATA
BlazeWeb-0.6.2.dist-info/WHEEL
BlazeWeb-0.6.2.dist-info/entry_points.txt
BlazeWeb-0.6.2.dist-info/top_level.txt
BlazeWeb-0.6.2.dist-info/RECORD
