Metadata-Version: 2.1
Name: BlazeWeb
Version: 0.6.2
Summary: A light weight WSGI framework with a pluggable architecture
Home-page: http://pypi.python.org/pypi/BlazeWeb/
Author: Randy Syring
Author-email: randy.syring@level12.io
License: BSD
Platform: UNKNOWN
Classifier: Development Status :: 4 - Beta
Classifier: Intended Audience :: Developers
Classifier: License :: OSI Approved :: BSD License
Classifier: Operating System :: OS Independent
Classifier: Programming Language :: Python :: 3.6
Classifier: Programming Language :: Python :: 3.7
Classifier: Programming Language :: Python :: 3.8
Classifier: Topic :: Internet :: WWW/HTTP
Requires-Dist: Beaker (>=1.5)
Requires-Dist: BlazeUtils (>0.3.7)
Requires-Dist: Blinker (>=1.0)
Requires-Dist: decorator (>=3.0.1)
Requires-Dist: FormEncode (>=1.2)
Requires-Dist: html2text (>=2.35)
Requires-Dist: jinja2 (>=2.5)
Requires-Dist: markdown2 (>=1.0.1)
Requires-Dist: Paste (>=1.7)
Requires-Dist: PasteScript (>=1.7)
Requires-Dist: WebHelpers2
Requires-Dist: Werkzeug (>=1.0.0)
Provides-Extra: develop
Requires-Dist: WebTest; extra == 'develop'
Requires-Dist: ScriptTest; extra == 'develop'
Requires-Dist: coverage; extra == 'develop'
Requires-Dist: docutils; extra == 'develop'
Requires-Dist: minimock; extra == 'develop'
Requires-Dist: nose; extra == 'develop'
